s3_ocr/__init__.py
s3_ocr/__main__.py
s3_ocr/cli.py
s3_ocr-0.6.3.dist-info/LICENSE
s3_ocr-0.6.3.dist-info/METADATA
s3_ocr-0.6.3.dist-info/WHEEL
s3_ocr-0.6.3.dist-info/entry_points.txt
s3_ocr-0.6.3.dist-info/top_level.txt
s3_ocr-0.6.3.dist-info/RECORD
