Metadata-Version: 2.1
Name: s3-ocr
Version: 0.6.3
Summary: Tools for running OCR against files stored in S3
Home-page: https://github.com/simonw/s3-ocr
Author: Simon Willison
License: Apache License, Version 2.0
Project-URL: Issues, https://github.com/simonw/s3-ocr/issues
Project-URL: CI, https://github.com/simonw/s3-ocr/actions
Project-URL: Changelog, https://github.com/simonw/s3-ocr/releases
Requires-Python: >=3.7
License-File: LICENSE
Requires-Dist: click (>=8.0)
Requires-Dist: boto3
Requires-Dist: sqlite-utils
Provides-Extra: test
Requires-Dist: pytest ; extra == 'test'
Requires-Dist: moto[s3,textract] ; extra == 'test'
Requires-Dist: cogapp ; extra == 'test'
Requires-Dist: pytest-mock ; extra == 'test'
